snweatherstation/__init__.py
snweatherstation/weatherForecastOWM.py
snweatherstation/weatherstation.py
snweatherstation/data/createDBtable.sql
snweatherstation/data/loggingConfig.json
snweatherstation/data/weatherstation.json
snweatherstation/data/weatherstation.service
snweatherstation-1.5.0.dist-info/LICENSE
snweatherstation-1.5.0.dist-info/METADATA
snweatherstation-1.5.0.dist-info/WHEEL
snweatherstation-1.5.0.dist-info/top_level.txt
snweatherstation-1.5.0.dist-info/RECORD
