Metadata-Version: 2.1
Name: snweatherstation
Version: 1.5.0
Summary: Another Raspberry Pi Weatherstation
Home-page: https://github.com/signag/snweatherstation
Author: signag
Author-email: siegfried.nagel@t-online.de
License: UNKNOWN
Project-URL: Source, https://github.com/signag/snweatherstation/
Keywords: RaspberryPi weatherstation
Platform: UNKNOWN
Classifier: Development Status :: 4 - Beta
Classifier: Intended Audience :: Developers
Classifier: Topic :: Software Development :: Build Tools
Classifier: License :: OSI Approved :: MIT License
Classifier: Programming Language :: Python :: 3
Requires-Python: >=3.5
Requires-Dist: adafruit-circuitpython-bme280 (==2.5.1)
Requires-Dist: adafruit-circuitpython-busdevice (==5.0.1)
Requires-Dist: adafruit-circuitpython-dht (==3.5.1)
Requires-Dist: mariadb (==1.0.5)
Requires-Dist: pyserial (==3.5)
Requires-Dist: pyusb (==1.1.0)
Requires-Dist: rpi.gpio (==0.7.0)
Requires-Dist: snraspi-lib (==1.0.2)
Requires-Dist: requests (==2.25.1)
Requires-Dist: adafruit-blinka (==5.9.1) ; python_full_version >= "3.5.0"
Requires-Dist: adafruit-platformdetect (==2.23.0) ; python_full_version >= "3.5.0"
Requires-Dist: adafruit-pureio (==1.1.8) ; python_full_version >= "3.5.0"
Requires-Dist: pyftdi (==0.52.0) ; python_full_version >= "3.5.0"
Requires-Dist: logging-plus (==1.0.0) ; python_version >= "3.6"
Provides-Extra: dev
